{
  "generated_utc": "2026-02-26T00:26:33Z",
  "version": 7,
  "naval_deployments": [
    {
      "id": "csg3",
      "name": "CSG-3 \u2014 USS Abraham Lincoln (CVN-72)",
      "type": "CSG",
      "flag": "\ud83c\uddfa\ud83c\uddf8",
      "location": "Western Pacific / 7th Fleet AOR",
      "lat": 13.5,
      "lng": 145.0,
      "status": "deployed",
      "notes": "Operating in Western Pacific, 7th Fleet. Conducting presence ops in SCS region."
    },
    {
      "id": "csg5",
      "name": "CSG-5 \u2014 USS Ronald Reagan (CVN-76)",
      "type": "CSG",
      "flag": "\ud83c\uddfa\ud83c\uddf8",
      "location": "Yokosuka, Japan (homeport \u2014 maintenance)",
      "lat": 35.3,
      "lng": 139.6,
      "status": "port",
      "notes": "Homeported Yokosuka. Reagan transitioning \u2014 Lincoln took over 7th Fleet duties."
    },
    {
      "id": "csg12",
      "name": "CSG-12 \u2014 USS Gerald R. Ford (CVN-78)",
      "type": "CSG",
      "flag": "\ud83c\uddfa\ud83c\uddf8",
      "location": "Eastern Mediterranean",
      "lat": 34.5,
      "lng": 30.0,
      "status": "deployed",
      "notes": "Operating in Eastern Med. Supporting regional deterrence amid Iran-Israel tensions."
    },
    {
      "id": "csg9",
      "name": "CSG-9 \u2014 USS Nimitz (CVN-68)",
      "type": "CSG",
      "flag": "\ud83c\uddfa\ud83c\uddf8",
      "location": "North Arabian Sea / 5th Fleet",
      "lat": 22.0,
      "lng": 62.0,
      "status": "deployed",
      "notes": "5th Fleet AOR. Supporting Red Sea/Houthi ops and Iran deterrence."
    },
    {
      "id": "arg_bataan",
      "name": "ARG \u2014 USS Bataan (LHD-5)",
      "type": "ARG",
      "flag": "\ud83c\uddfa\ud83c\uddf8",
      "location": "Mediterranean Sea",
      "lat": 37.0,
      "lng": 15.0,
      "status": "deployed",
      "notes": "MEU embarked. Operating in Med with NATO partners."
    },
    {
      "id": "arg_boxer",
      "name": "ARG \u2014 USS Boxer (LHD-4)",
      "type": "ARG",
      "flag": "\ud83c\uddfa\ud83c\uddf8",
      "location": "San Diego, CA (maintenance)",
      "lat": 32.7,
      "lng": -117.2,
      "status": "port",
      "notes": "In port San Diego undergoing scheduled maintenance."
    },
    {
      "id": "ssbn_atl",
      "name": "SSBN Patrol \u2014 Atlantic",
      "type": "SSBN",
      "flag": "\ud83c\uddfa\ud83c\uddf8",
      "location": "North Atlantic (classified)",
      "lat": 55.0,
      "lng": -35.0,
      "status": "deployed",
      "notes": "Ohio-class SSBN on deterrent patrol. Location classified."
    },
    {
      "id": "ssbn_pac",
      "name": "SSBN Patrol \u2014 Pacific",
      "type": "SSBN",
      "flag": "\ud83c\uddfa\ud83c\uddf8",
      "location": "Pacific Ocean (classified)",
      "lat": 40.0,
      "lng": -150.0,
      "status": "deployed",
      "notes": "Ohio-class SSBN on deterrent patrol. Location classified."
    },
    {
      "id": "ru_north",
      "name": "\ud83c\uddf7\ud83c\uddfa Northern Fleet \u2014 Severomorsk",
      "type": "Fleet",
      "flag": "\ud83c\uddf7\ud83c\uddfa",
      "location": "Severomorsk / Barents Sea",
      "lat": 69.1,
      "lng": 33.4,
      "status": "combat",
      "notes": "Reduced activity. Several vessels undergoing repair after combat losses in Black Sea campaign."
    },
    {
      "id": "ru_black",
      "name": "\ud83c\uddf7\ud83c\uddfa Black Sea Fleet \u2014 Sevastopol",
      "type": "Fleet",
      "flag": "\ud83c\uddf7\ud83c\uddfa",
      "location": "Novorossiysk (relocated from Sevastopol)",
      "lat": 44.7,
      "lng": 37.8,
      "status": "combat",
      "notes": "Fleet largely relocated to Novorossiysk after Ukrainian drone/missile strikes on Sevastopol. Significantly degraded."
    },
    {
      "id": "cn_south",
      "name": "\ud83c\udde8\ud83c\uddf3 PLA Navy \u2014 South Sea Fleet",
      "type": "Fleet",
      "flag": "\ud83c\udde8\ud83c\uddf3",
      "location": "South China Sea / Sanya Naval Base",
      "lat": 18.2,
      "lng": 109.5,
      "status": "deployed",
      "notes": "Carrier Fujian conducting training ops. Heightened activity near Taiwan Strait."
    },
    {
      "id": "ir_irin",
      "name": "\ud83c\uddee\ud83c\uddf7 IRIN \u2014 Bandar Abbas",
      "type": "Fleet",
      "flag": "\ud83c\uddee\ud83c\uddf7",
      "location": "Persian Gulf / Strait of Hormuz",
      "lat": 27.2,
      "lng": 56.3,
      "status": "elevated",
      "notes": "IRGCN fast-boats active in Gulf. US-Iran nuclear talks ongoing in Geneva (Feb 26). Posture cautiously elevated."
    }
  ],
  "chokepoints": [
    {
      "name": "Strait of Hormuz",
      "status": "ELEVATED",
      "lat": 26.6,
      "lon": 56.3,
      "note": "Iranian naval posturing \u2014 IRGCN fast boats active"
    },
    {
      "name": "Bab el-Mandeb",
      "status": "HIGH RISK",
      "lat": 12.6,
      "lon": 43.3,
      "note": "Houthi anti-ship missile/drone threat \u2014 coalition patrols active"
    },
    {
      "name": "Taiwan Strait",
      "status": "WATCH",
      "lat": 24.5,
      "lon": 119.5,
      "note": "PLA Navy exercises \u2014 US transits ongoing"
    },
    {
      "name": "Suez Canal",
      "status": "NORMAL",
      "lat": 30.5,
      "lon": 32.3,
      "note": "Operating normally \u2014 traffic diversions from Red Sea"
    },
    {
      "name": "GIUK Gap",
      "status": "WATCH",
      "lat": 62.0,
      "lon": -15.0,
      "note": "Russian submarine transit monitoring \u2014 P-8 patrols"
    },
    {
      "name": "Malacca Strait",
      "status": "NORMAL",
      "lat": 2.5,
      "lon": 101.5,
      "note": "Normal commercial traffic"
    }
  ],
  "conflicts": [
    {
      "id": "ukraine",
      "name": "Ukraine-Russia War",
      "lat": 49.0,
      "lng": 32.0,
      "intensity": "HIGH",
      "status": "ACTIVE COMBAT",
      "update": "Zelenskyy spoke with Trump Feb 25 re: peace talks. US-Ukraine envoys meeting Geneva Feb 26. Russia recruiting 1,700+ African mercenaries per Ukraine intel. Frontlines largely static in Donbas."
    },
    {
      "id": "gaza",
      "name": "Gaza Conflict",
      "lat": 31.5,
      "lng": 34.5,
      "intensity": "HIGH",
      "status": "ACTIVE COMBAT",
      "update": "Modi addressed Israeli Knesset Feb 25. Hostage negotiations ongoing. IDF continuing operations in Gaza. Modi: 'No cause justifies killing civilians.'"
    },
    {
      "id": "redsea",
      "name": "Red Sea / Houthi Campaign",
      "lat": 15.5,
      "lng": 42.5,
      "intensity": "MEDIUM",
      "status": "ACTIVE",
      "update": "Houthi attacks on shipping continuing. US Navy (Nimitz CSG) maintaining presence in North Arabian Sea. Commercial traffic rerouting via Cape of Good Hope."
    },
    {
      "id": "lebanon",
      "name": "Israel-Lebanon Border",
      "lat": 33.3,
      "lng": 35.5,
      "intensity": "LOW",
      "status": "CEASEFIRE HOLDING",
      "update": "Ceasefire largely holding. IDF maintaining buffer zone in southern Lebanon. Sporadic incidents reported but no major escalation."
    },
    {
      "id": "syria",
      "name": "Syria \u2014 Post-Assad Transition",
      "lat": 35.0,
      "lng": 38.5,
      "intensity": "LOW",
      "status": "TRANSITIONAL",
      "update": "HTS-led government consolidating control. Turkey, US, Israel all maintaining forces/influence. ISIS remnants active in eastern Syria."
    },
    {
      "id": "taiwan",
      "name": "Taiwan Strait Tensions",
      "lat": 23.5,
      "lng": 120.5,
      "intensity": "MEDIUM",
      "status": "ELEVATED",
      "update": "PLA Fujian carrier conducting drills near strait. Philippines People Power anniversary protests. US maintaining freedom of navigation transits."
    },
    {
      "id": "scs",
      "name": "South China Sea Disputes",
      "lat": 12.0,
      "lng": 114.0,
      "intensity": "MEDIUM",
      "status": "ELEVATED",
      "update": "PLA Navy activity elevated near Spratly Islands. Philippines-China standoffs continuing at Second Thomas Shoal. US presence maintained."
    },
    {
      "id": "iran",
      "name": "Iran-Israel / US-Iran Tensions",
      "lat": 32.0,
      "lng": 53.0,
      "intensity": "MEDIUM",
      "status": "NEGOTIATING",
      "update": "US-Iran nuclear talks in Geneva Feb 26. Trump weighing options post-State of the Union. Next round could be decisive. Ford CSG in Eastern Med as deterrent backdrop."
    }
  ],
  "exercises": [
    {
      "id": "defender26",
      "name": "DEFENDER EUROPE 2026",
      "status": "PLANNED",
      "dates": "May\u2013Jun 2026",
      "location": "Europe (multi-nation)",
      "participants": "NATO allies, ~20,000 US troops",
      "notes": "Annual large-scale NATO exercise. Planning underway."
    },
    {
      "id": "rimpac26",
      "name": "RIMPAC 2026",
      "status": "PLANNED",
      "dates": "Jun\u2013Aug 2026",
      "location": "Hawaii / Pacific",
      "participants": "~25 nations, 3+ carrier groups",
      "notes": "World's largest naval exercise. Biennial."
    },
    {
      "id": "steadfast",
      "name": "STEADFAST DEFENDER 2026",
      "status": "PLANNING",
      "dates": "Early 2026",
      "location": "Eastern Europe / Baltics",
      "participants": "NATO",
      "notes": "NATO's largest defensive exercise. Focus on eastern flank defense."
    },
    {
      "id": "cobragold",
      "name": "COBRA GOLD 2026",
      "status": "ONGOING",
      "dates": "Feb 25 \u2013 Mar 7, 2026",
      "location": "Thailand",
      "participants": "US, Thailand, Japan, Singapore, Indonesia, Malaysia, South Korea",
      "notes": "Largest multilateral exercise in Indo-Pacific. Currently active as of Feb 25."
    },
    {
      "id": "keensword",
      "name": "KEEN SWORD 2026",
      "status": "COMPLETED",
      "dates": "Oct\u2013Nov 2025",
      "location": "Japan",
      "participants": "US, Japan",
      "notes": "Completed. Biennial US-Japan bilateral. Next edition 2027."
    },
    {
      "id": "vostok",
      "name": "VOSTOK (Russia)",
      "status": "PLANNED",
      "dates": "Sep 2026 (est.)",
      "location": "Eastern Russia",
      "participants": "Russia, China, CSTO",
      "notes": "Annual Russian strategic exercise in Eastern Military District."
    },
    {
      "id": "jointsword",
      "name": "JOINT SWORD (China)",
      "status": "WATCH",
      "dates": "On demand",
      "location": "Taiwan Strait region",
      "participants": "PLA (all services)",
      "notes": "China conducts unannounced JOINT SWORD exercises in response to Taiwan events. Monitor for triggers."
    },
    {
      "id": "redflag",
      "name": "RED FLAG 26-1",
      "status": "COMPLETED",
      "dates": "Jan 2026",
      "location": "Nellis AFB, Nevada",
      "participants": "USAF, allied air forces",
      "notes": "First RED FLAG of 2026 completed. RED FLAG 26-2 planned for spring."
    }
  ],
  "gps_zones": [
    {
      "id": "ukraine_east",
      "name": "Eastern Ukraine / Donbas",
      "lat": 48.5,
      "lng": 37.5,
      "radius_km": 200,
      "active": true,
      "notes": "Active Russian GPS jamming and spoofing. Affects both military and civil aviation."
    },
    {
      "id": "finland_nord",
      "name": "Northern Finland / Lapland",
      "lat": 68.0,
      "lng": 27.0,
      "radius_km": 150,
      "active": true,
      "notes": "Russian jamming from Kola Peninsula affecting Finnish and Norwegian airspace. Ongoing."
    },
    {
      "id": "baltics",
      "name": "Baltic States",
      "lat": 57.0,
      "lng": 24.0,
      "radius_km": 200,
      "active": true,
      "notes": "Intermittent Russian jamming. Estonia, Latvia, Lithuania affected. NATO monitoring."
    },
    {
      "id": "blacksea",
      "name": "Black Sea / Romania",
      "lat": 44.0,
      "lng": 30.0,
      "radius_km": 250,
      "active": true,
      "notes": "Spoofing incidents reported over Black Sea. Vessels reporting false positions."
    },
    {
      "id": "israel",
      "name": "Israel / Eastern Mediterranean",
      "lat": 32.5,
      "lng": 35.5,
      "radius_km": 200,
      "active": true,
      "notes": "Active GPS jamming by IDF over Israel and Lebanon. Ongoing since Oct 2023 war."
    },
    {
      "id": "syria_iraq",
      "name": "Syria / Iraq border",
      "lat": 34.5,
      "lng": 41.0,
      "radius_km": 200,
      "active": true,
      "notes": "Multi-source jamming. US, Russian, Turkish forces all operating jamming systems."
    },
    {
      "id": "red_sea",
      "name": "Red Sea / Yemen",
      "lat": 15.0,
      "lng": 43.0,
      "radius_km": 200,
      "active": true,
      "notes": "Houthi spoofing affecting commercial shipping navigation. Incidents ongoing."
    },
    {
      "id": "taiwan_str",
      "name": "Taiwan Strait",
      "lat": 24.0,
      "lng": 120.0,
      "radius_km": 150,
      "active": true,
      "notes": "PLA jamming exercises. Intermittent disruption to civil aviation."
    },
    {
      "id": "scs_spratlys",
      "name": "South China Sea \u2014 Spratly Islands",
      "lat": 10.0,
      "lng": 114.0,
      "radius_km": 200,
      "active": true,
      "notes": "Chinese jamming operations around artificial islands. Reported by Philippine vessels."
    },
    {
      "id": "kaliningrad",
      "name": "Kaliningrad / Poland border",
      "lat": 54.7,
      "lng": 20.5,
      "radius_km": 150,
      "active": true,
      "notes": "Russian Kaliningrad exclave jamming affecting NE Poland and Lithuania airspace."
    },
    {
      "id": "iran_gulf",
      "name": "Persian Gulf / Hormuz",
      "lat": 26.5,
      "lng": 56.0,
      "radius_km": 150,
      "active": false,
      "notes": "Intermittent Iranian GPS spoofing. Reduced since nuclear talks began but not eliminated."
    }
  ],
  "notams": [
    {
      "id": "notam_ukraine",
      "name": "Ukraine Airspace NOTAM",
      "lat": 49.0,
      "lng": 32.0,
      "radius_km": 500,
      "active": true,
      "type": "warzone",
      "notes": "Ukrainian airspace fully closed to civil aviation. Active conflict."
    },
    {
      "id": "notam_israel",
      "name": "Israel / Gaza TFR",
      "lat": 31.8,
      "lng": 34.8,
      "radius_km": 150,
      "active": true,
      "type": "combat",
      "notes": "TFR active over Gaza and southern Israel. Limited civil ops from TLV with restrictions."
    },
    {
      "id": "notam_redsea",
      "name": "Red Sea NOTAM",
      "lat": 15.0,
      "lng": 42.0,
      "radius_km": 300,
      "active": true,
      "type": "maritime_threat",
      "notes": "UKMTO and US Navy warnings active. Commercial vessels avoiding core Red Sea lanes."
    },
    {
      "id": "notam_lebanon",
      "name": "Lebanon Airspace Restrictions",
      "lat": 33.8,
      "lng": 35.5,
      "radius_km": 100,
      "active": true,
      "type": "conflict",
      "notes": "Beirut airport operational but restrictions active in south Lebanon."
    },
    {
      "id": "notam_iran",
      "name": "Iran ADIZ Alert",
      "lat": 33.0,
      "lng": 53.0,
      "radius_km": 400,
      "active": true,
      "type": "adiz",
      "notes": "Heightened Iranian air defense posture during Geneva talks. Monitor for changes."
    },
    {
      "id": "notam_taiwan",
      "name": "Taiwan Strait Notice",
      "lat": 24.0,
      "lng": 120.5,
      "radius_km": 200,
      "active": true,
      "type": "military_activity",
      "notes": "PLA military activity in strait. Airlines rerouting. Monitor for JOINT SWORD trigger."
    },
    {
      "id": "notam_baltics",
      "name": "Baltic Air Policing",
      "lat": 57.0,
      "lng": 24.0,
      "radius_km": 200,
      "active": true,
      "type": "air_policing",
      "notes": "NATO Enhanced Air Policing active. Increased intercept activity of Russian aircraft."
    },
    {
      "id": "notam_nevada",
      "name": "Red Flag 26-1 TFR (expired)",
      "lat": 37.2,
      "lng": -115.8,
      "radius_km": 100,
      "active": false,
      "type": "exercise",
      "notes": "RED FLAG 26-1 completed Jan 2026. Next exercise TFR expected spring."
    },
    {
      "id": "notam_nkorea",
      "name": "North Korea ADIZ / Exclusion",
      "lat": 39.0,
      "lng": 127.5,
      "radius_km": 300,
      "active": true,
      "type": "exclusion",
      "notes": "North Korean airspace fully restricted. Recent missile tests. ICAO warnings active."
    },
    {
      "id": "notam_sudan",
      "name": "Sudan Airspace NOTAM",
      "lat": 15.5,
      "lng": 32.0,
      "radius_km": 400,
      "active": true,
      "type": "conflict",
      "notes": "RSF-SAF civil war ongoing. Khartoum area dangerous. Sporadic airspace closures."
    }
  ],
  "_naval_news_refs": [
    {
      "title": "As aging Air Force AWACS heads to Middle East, where is its replacement?",
      "link": "https://taskandpurpose.com/news/air-force-awacs-replacement-video/",
      "published": "Fri, 20 Feb 2026 14:05:36 -0500",
      "source": "Task & Purpose",
      "categories": [
        "deployment"
      ]
    },
    {
      "title": "USS Gerald R. Ford Now in the Mediterranean Sea, More U.S. Forces Deploy to Middle East",
      "link": "https://news.usni.org/2026/02/20/uss-gerald-r-ford-now-in-the-mediterranean-sea-2",
      "published": "Fri, 20 Feb 2026 15:04:29 +0000",
      "source": "USNI News",
      "categories": [
        "deployment"
      ]
    },
    {
      "title": "U.S., Philippines Commit to Increased Missile, Drone Deployments in First Island Chain",
      "link": "https://news.usni.org/2026/02/20/u-s-philippines-commit-to-increased-missile-drone-deployments-in-first-island-chain",
      "published": "Fri, 20 Feb 2026 21:02:01 +0000",
      "source": "USNI News",
      "categories": [
        "deployment",
        "conflict"
      ]
    },
    {
      "title": "Massive US Air Force warplane movements in Bulgaria raise stakes for Iran talks",
      "link": "https://www.defensenews.com/global/europe/2026/02/23/massive-us-air-force-warplane-movements-in-bulgaria-raise-stakes-for-iran-talks/",
      "published": "Mon, 23 Feb 2026 10:54:14 +0000",
      "source": "Defense News",
      "categories": [
        "deployment"
      ]
    },
    {
      "title": "USNI News Fleet and Marine Tracker: Feb. 23, 2026",
      "link": "https://news.usni.org/2026/02/23/usni-news-fleet-and-marine-tracker-feb-23-2026",
      "published": "Mon, 23 Feb 2026 19:34:20 +0000",
      "source": "USNI News",
      "categories": [
        "deployment"
      ]
    },
    {
      "title": "US pulls nonessential staff from Beirut embassy as tensions with Iran ratchet up",
      "link": "https://www.militarytimes.com/news/pentagon-congress/2026/02/23/us-pulls-nonessential-staff-from-beirut-embassy-as-tensions-with-iran-ratchet-up/",
      "published": "Mon, 23 Feb 2026 21:20:08 +0000",
      "source": "Military Times",
      "categories": [
        "deployment"
      ]
    },
    {
      "title": "French Carrier Strike Group Heading to North Atlantic, Baltic",
      "link": "https://news.usni.org/2026/02/23/french-carrier-strike-group-heading-to-north-atlantic-baltic",
      "published": "Mon, 23 Feb 2026 22:11:32 +0000",
      "source": "USNI News",
      "categories": [
        "deployment",
        "conflict"
      ]
    },
    {
      "title": "French aircraft carrier begins Baltic Sea and North Atlantic deployment",
      "link": "https://www.navalnews.com/naval-news/2026/02/french-aircraft-carrier-begins-baltic-sea-and-north-atlantic-deployment/",
      "published": "Sun, 22 Feb 2026 09:06:08 +0000",
      "source": "Naval News",
      "categories": [
        "deployment"
      ]
    },
    {
      "title": "Danish military evacuates US submariner who needed urgent medical care off Greenland",
      "link": "https://www.defensenews.com/news/your-military/2026/02/22/danish-military-evacuates-us-submariner-who-needed-urgent-medical-care-off-greenland/",
      "published": "Sun, 22 Feb 2026 14:08:24 +0000",
      "source": "Defense News",
      "categories": [
        "deployment"
      ]
    },
    {
      "title": "Navy relieves destroyer commander after Caribbean crash",
      "link": "https://taskandpurpose.com/news/navy-relieves-truxtun-james-koffi/",
      "published": "Sun, 22 Feb 2026 20:20:10 -0500",
      "source": "Task & Purpose",
      "categories": [
        "deployment"
      ]
    }
  ],
  "centcom_assets": {
    "updated": "2026-02-26T00:26:33Z",
    "summary": "Two carrier strike groups in CENTCOM/EUCOM AOR. Ford in Eastern Med, Nimitz in North Arabian Sea. US-Iran nuclear talks in Geneva Feb 26 \u2014 posture cautiously elevated. Houthi campaign ongoing in Red Sea.",
    "troops_total": "~40,000",
    "naval": "2 CSGs (Ford, Nimitz), multiple destroyers/cruisers",
    "air": "F-22, F-35, B-52 forward deployed",
    "ground": "Pre-positioned forces Kuwait, Qatar, UAE, Bahrain"
  },
  "_conflict_news_refs": [
    {
      "title": "U.S., Philippines Commit to Increased Missile, Drone Deployments in First Island Chain",
      "link": "https://news.usni.org/2026/02/20/u-s-philippines-commit-to-increased-missile-drone-deployments-in-first-island-chain",
      "published": "Fri, 20 Feb 2026 21:02:01 +0000",
      "source": "USNI News",
      "categories": [
        "deployment",
        "conflict"
      ]
    },
    {
      "title": "U.S. Conducts Strikes in Eastern Pacific, Caribbean, Killing 6",
      "link": "https://news.usni.org/2026/02/23/u-s-conducts-strikes-in-eastern-pacific-caribbean-killing-6",
      "published": "Mon, 23 Feb 2026 20:34:34 +0000",
      "source": "USNI News",
      "categories": [
        "conflict"
      ]
    },
    {
      "title": "French Carrier Strike Group Heading to North Atlantic, Baltic",
      "link": "https://news.usni.org/2026/02/23/french-carrier-strike-group-heading-to-north-atlantic-baltic",
      "published": "Mon, 23 Feb 2026 22:11:32 +0000",
      "source": "USNI News",
      "categories": [
        "deployment",
        "conflict"
      ]
    },
    {
      "title": "Philippine Navy commissions new patrol vessel, missile boat",
      "link": "https://www.navalnews.com/naval-news/2026/02/philippine-navy-commissions-new-patrol-vessel-missile-boat/",
      "published": "Tue, 24 Feb 2026 11:22:10 +0000",
      "source": "Naval News",
      "categories": [
        "conflict"
      ]
    }
  ],
  "_exercise_news_refs": [
    {
      "title": "U.S., Japan Air Forces Conduct Joint Drills with 4 American Bombers",
      "link": "https://news.usni.org/2026/02/20/u-s-japan-air-forces-conduct-joint-drills-with-4-american-bombers",
      "published": "Fri, 20 Feb 2026 19:31:47 +0000",
      "source": "USNI News",
      "categories": [
        "exercise"
      ]
    },
    {
      "title": "NATO is not ready for drone warfare in the Arctic",
      "link": "https://www.defensenews.com/opinion/2026/02/23/nato-is-not-ready-for-drone-warfare-in-the-arctic/",
      "published": "Mon, 23 Feb 2026 10:21:48 +0000",
      "source": "Defense News",
      "categories": [
        "exercise"
      ]
    },
    {
      "title": "F-22 Raptor, MQ-20 drone complete manned-unmanned flight exercise",
      "link": "https://www.defensenews.com/industry/techwatch/2026/02/23/f-22-raptor-mq-20-drone-complete-manned-unmanned-flight-exercise/",
      "published": "Mon, 23 Feb 2026 19:35:55 +0000",
      "source": "Defense News",
      "categories": [
        "exercise"
      ]
    },
    {
      "title": "F-22 Raptor, MQ-20 drone complete manned-unmanned flight exercise",
      "link": "https://www.militarytimes.com/industry/techwatch/2026/02/23/f-22-raptor-mq-20-drone-complete-manned-unmanned-flight-exercise/",
      "published": "Mon, 23 Feb 2026 19:35:55 +0000",
      "source": "Military Times",
      "categories": [
        "exercise"
      ]
    }
  ],
  "_threat_indicators": {
    "deployment_articles": 8,
    "conflict_articles": 12,
    "exercise_articles": 5,
    "total_articles": 50,
    "computed_at": "2026-02-26T00:26:33Z",
    "top_signals": [
      "US-Iran Geneva talks (Feb 26) \u2014 decisive round",
      "Zelenskyy-Trump peace diplomacy active",
      "PLA Fujian carrier exercises near Taiwan Strait",
      "Russia recruiting African mercenaries for Ukraine",
      "Modi in Israel \u2014 India-Israel partnership deepening",
      "COBRA GOLD 2026 ongoing in Thailand"
    ]
  }
}